pydb/__init__.py
pydb/client.py
pydb/exceptions.py
pydb/exporter.py
pydb/logger.py
pydb/main.py
pydb/reader.py
pydb/zipper.py
pydb/dbms/__init__.py
pydb/dbms/arguments.py
pydb/dbms/connector.py
pydb/dbms/constants.py
pydb/dbms/mssql.py
pydb/dbms/mysql.py
pydb/dbms/object_factory.py
pydb/dbms/oracle.py
pydb/dbms/postgresql.py
xdbcli-1.5.1.dist-info/licenses/LICENSE
xdbcli-1.5.1.dist-info/METADATA
xdbcli-1.5.1.dist-info/WHEEL
xdbcli-1.5.1.dist-info/entry_points.txt
xdbcli-1.5.1.dist-info/top_level.txt
xdbcli-1.5.1.dist-info/RECORD
