Metadata-Version: 2.4
Name: xdbcli
Version: 1.5.1
Summary: Light CLI Oracle, Postgres, Mysql, Mssql
Author-email: Aleksandr Shabelsky <a.shabelsky@gmail.com>
License: MIT License
Project-URL: Homepage, https://github.com/shabelski89/pydb
Project-URL: Bug Tracker, https://github.com/shabelski89/pydb/issues
Classifier: Programming Language :: Python :: 3
Classifier: License :: OSI Approved :: MIT License
Classifier: Operating System :: OS Independent
Requires-Python: >=3.6
License-File: LICENSE
Requires-Dist: colorama==0.4.4
Requires-Dist: pep517==0.12.0
Requires-Dist: wcwidth==0.2.5
Requires-Dist: zipp==3.6.0
Requires-Dist: pyparsing==3.0.7
Requires-Dist: tomli==1.2.3
Requires-Dist: typing_extensions==4.1.1
Requires-Dist: importlib-metadata==4.8.3
Requires-Dist: prettytable==2.5.0
Requires-Dist: cffi==1.15.1
Requires-Dist: cryptography==40.0.2
Requires-Dist: pycparser==2.21
Provides-Extra: oracle
Requires-Dist: oracledb==1.4.2; extra == "oracle"
Provides-Extra: postgres
Requires-Dist: psycopg2-binary==2.9.1; extra == "postgres"
Provides-Extra: mysql
Requires-Dist: PyMySQL==1.0.2; extra == "mysql"
Provides-Extra: mssql
Requires-Dist: JayDeBeApi==1.2.3; extra == "mssql"
Dynamic: license-file
